streamlit_selectable_image_gallery/__init__.py
streamlit_selectable_image_gallery/frontend/build/asset-manifest.json
streamlit_selectable_image_gallery/frontend/build/bootstrap.min.css
streamlit_selectable_image_gallery/frontend/build/index.html
streamlit_selectable_image_gallery/frontend/build/static/js/main.3bb0f0fc.js
streamlit_selectable_image_gallery/frontend/build/static/js/main.3bb0f0fc.js.LICENSE.txt
streamlit_selectable_image_gallery/frontend/build/static/js/main.3bb0f0fc.js.map
streamlit_selectable_image_gallery-0.0.1.dist-info/LICENSE
streamlit_selectable_image_gallery-0.0.1.dist-info/METADATA
streamlit_selectable_image_gallery-0.0.1.dist-info/WHEEL
streamlit_selectable_image_gallery-0.0.1.dist-info/top_level.txt
streamlit_selectable_image_gallery-0.0.1.dist-info/RECORD
