Metadata-Version: 2.1
Name: streamlit-selectable-image-gallery
Version: 0.0.1
Summary: Streamlit component that allows you to do have a gallery of image and select one of them.
Home-page: 
Author: Gasmain
Author-email: gasparguillemain@gmail.com
Requires-Python: >=3.7
License-File: LICENSE
Requires-Dist: streamlit (>=0.63)
